Metadata-Version: 2.1
Name: Federated-Learning-Server
Version: 0.0.12
Summary: Server package for Collaborative learning framework for deep neural network
Home-page: https://github.com/sHOTa-23/Collaborative-Learning-Framework-for-Deep-Neural-Network
Author: Bichebi
Author-email: mgach18@freeuni.edu.ge
License: UNKNOWN
Platform: UNKNOWN
